vtracker/__init__.py
vtracker/exceptions.py
vtracker/graph.py
vtracker/vtracker.py
vtracker-1.0.1.data/data/LICENSE
vtracker-1.0.1.dist-info/LICENSE
vtracker-1.0.1.dist-info/METADATA
vtracker-1.0.1.dist-info/WHEEL
vtracker-1.0.1.dist-info/top_level.txt
vtracker-1.0.1.dist-info/RECORD
