Metadata-Version: 2.1
Name: vtracker
Version: 1.0.1
Summary: For tracking the relationship between group membership changes across versions.
Home-page: https://github.com/aaronmussig/VTracker
Author: Aaron Mussig
Author-email: aaronmussig@gmail.com
License: GPL3
Project-URL: Bug Tracker, https://github.com/aaronmussig/VTracker/issues
Project-URL: Documentation, https://github.com/aaronmussig/VTracker
Project-URL: Source Code, https://github.com/aaronmussig/VTracker
Keywords: track relationship group membership version
Platform: UNKNOWN
Classifier: Development Status :: 5 - Production/Stable
Classifier: Intended Audience :: Science/Research
Classifier: License :: OSI Approved :: GNU General Public License v3 (GPLv3)
Classifier: Natural Language :: English
Classifier: Operating System :: OS Independent
Classifier: Programming Language :: Python :: 2
Classifier: Programming Language :: Python :: 3
Classifier: Topic :: Scientific/Engineering
Requires-Python: >=2.7
Requires-Dist: typing
